blazar_dashboard/__init__.py
blazar_dashboard/conf.py
blazar_dashboard/version.py
blazar_dashboard/api/__init__.py
blazar_dashboard/api/client.py
blazar_dashboard/content/__init__.py
blazar_dashboard/content/hosts/__init__.py
blazar_dashboard/content/hosts/forms.py
blazar_dashboard/content/hosts/panel.py
blazar_dashboard/content/hosts/tables.py
blazar_dashboard/content/hosts/tabs.py
blazar_dashboard/content/hosts/tests.py
blazar_dashboard/content/hosts/urls.py
blazar_dashboard/content/hosts/views.py
blazar_dashboard/content/hosts/workflows.py
blazar_dashboard/content/hosts/templates/hosts/_detail_overview.html
blazar_dashboard/content/hosts/templates/hosts/_update.html
blazar_dashboard/content/hosts/templates/hosts/create.html
blazar_dashboard/content/hosts/templates/hosts/detail.html
blazar_dashboard/content/hosts/templates/hosts/index.html
blazar_dashboard/content/hosts/templates/hosts/update.html
blazar_dashboard/content/leases/__init__.py
blazar_dashboard/content/leases/forms.py
blazar_dashboard/content/leases/panel.py
blazar_dashboard/content/leases/tables.py
blazar_dashboard/content/leases/tabs.py
blazar_dashboard/content/leases/tests.py
blazar_dashboard/content/leases/urls.py
blazar_dashboard/content/leases/views.py
blazar_dashboard/content/leases/templates/leases/_create.html
blazar_dashboard/content/leases/templates/leases/_detail_overview.html
blazar_dashboard/content/leases/templates/leases/_update.html
blazar_dashboard/content/leases/templates/leases/calendar.html
blazar_dashboard/content/leases/templates/leases/create.html
blazar_dashboard/content/leases/templates/leases/detail.html
blazar_dashboard/content/leases/templates/leases/index.html
blazar_dashboard/content/leases/templates/leases/update.html
blazar_dashboard/enabled/_90_admin_reservation_panelgroup.py
blazar_dashboard/enabled/_90_project_reservations_panelgroup.py
blazar_dashboard/enabled/_91_admin_reservation_hosts_panel.py
blazar_dashboard/enabled/_91_project_reservations_leases_panel.py
blazar_dashboard-14.0.0.dist-info/AUTHORS
blazar_dashboard-14.0.0.dist-info/LICENSE
blazar_dashboard-14.0.0.dist-info/METADATA
blazar_dashboard-14.0.0.dist-info/WHEEL
blazar_dashboard-14.0.0.dist-info/pbr.json
blazar_dashboard-14.0.0.dist-info/top_level.txt
blazar_dashboard-14.0.0.dist-info/RECORD
